ecl_logging_utility/__init__.py
ecl_logging_utility/logging_utility.py
ecl_logging_utility/slack_session_manager.py
ecl_logging_utility-1.0.18.dist-info/METADATA
ecl_logging_utility-1.0.18.dist-info/WHEEL
ecl_logging_utility-1.0.18.dist-info/top_level.txt
ecl_logging_utility-1.0.18.dist-info/RECORD
