Metadata-Version: 2.4
Name: ecl-logging-utility
Version: 1.0.18
Summary: Internal structured logging utility for ECL microservices
Classifier: Programming Language :: Python :: 3
Classifier: License :: Other/Proprietary License
Classifier: Operating System :: OS Independent
Requires-Python: >=3.8
Requires-Dist: structlog>=23.1.0
Requires-Dist: python-json-logger>=2.0.2
Requires-Dist: opensearch-py>=2.6.0
Dynamic: classifier
Dynamic: description
Dynamic: description-content-type
Dynamic: requires-dist
Dynamic: requires-python
Dynamic: summary
